{
    "votes": [
        {
            "id": "3",
            "vote": "James Davies (Party G)",
            "code": "1JkBJzTd-3YhNxjWj"
        },
        {
            "id": "5",
            "vote": "James Davies (Party G)",
            "code": "3giIylBv-KI090U36"
        },
        {
            "id": "6",
            "vote": "James Davies (Party G)",
            "code": "3iA0DoA8-MAlM82PX"
        },
        {
            "id": "8",
            "vote": "Sarah Wilson (Party F)",
            "code": "5MSi5ZMX-rwOc8gT9"
        },
        {
            "id": "9",
            "vote": "Sarah Wilson (Party F)",
            "code": "6HsPsNQB-mQZqlyQy"
        },
        {
            "id": "11",
            "vote": "Mark Jones (Party B)",
            "code": "8d6NdNpF-oGyxmvcB"
        },
        {
            "id": "12",
            "vote": "Mark Jones (Party B)",
            "code": "AY3pjJ3c-QzGpPWu9"
        },
        {
            "id": "13",
            "vote": "Sarah Wilson (Party F)",
            "code": "BFIPdETftgnPXYu-jmokvyWa"
        },
        {
            "id": "15",
            "vote": "Mark Jones (Party B)",
            "code": "C5aJS3P0saZOAvU-qVQQkUA2"
        },
        {
            "id": "18",
            "vote": "Mark Jones (Party B)",
            "code": "Cwj9qdPZ-hdagjxeV"
        },
        {
            "id": "19",
            "vote": "Sarah Wilson (Party F)",
            "code": "DDtnmI8X-LqQBhMdp"
        },
        {
            "id": "23",
            "vote": "Alice Smith (Party A)",
            "code": "Fpz7XXSEnALj6JE-lF0Ejibj"
        },
        {
            "id": "24",
            "vote": "Mark Jones (Party B)",
            "code": "GSj7fSfbNtIR0PD-YAH2rjVR"
        },
        {
            "id": "28",
            "vote": "Mark Jones (Party B)",
            "code": "JSkA0fo25xXqiPD-GsogTVOM"
        },
        {
            "id": "29",
            "vote": "James Davies (Party G)",
            "code": "JWjQSfv2rhkFhnq-X1V6T6cx"
        },
        {
            "id": "30",
            "vote": "James Davies (Party G)",
            "code": "JkBYrcsG-XGJF9JU1"
        },
        {
            "id": "33",
            "vote": "Sarah Wilson (Party F)",
            "code": "N0LgnNfI9VwjGgo-2ORNhcnb"
        },
        {
            "id": "36",
            "vote": "Mark Jones (Party B)",
            "code": "OJtI0FANOsmzoDG-ySc24xdH"
        },
        {
            "id": "37",
            "vote": "Sarah Wilson (Party F)",
            "code": "OrpapjKy-KLL5jb7k"
        },
        {
            "id": "38",
            "vote": "James Davies (Party G)",
            "code": "P1u6eqdUie0RXwp-k5WKVFcN"
        },
        {
            "id": "42",
            "vote": "Sarah Wilson (Party F)",
            "code": "Q2usuqxh-EU3qoDtp"
        },
        {
            "id": "45",
            "vote": "Sarah Wilson (Party F)",
            "code": "QTRfTjwy-JQnINn8L"
        },
        {
            "id": "48",
            "vote": "James Davies (Party G)",
            "code": "TNqXVLQofNfbN3A-AjQXQd4G"
        },
        {
            "id": "49",
            "vote": "Alice Smith (Party A)",
            "code": "TjXoLuOK-wQxDVnEZ"
        },
        {
            "id": "50",
            "vote": "Sarah Wilson (Party F)",
            "code": "UWOsD8OxkGTiKv6-Gp43RqaJ"
        },
        {
            "id": "51",
            "vote": "Sarah Wilson (Party F)",
            "code": "VEllDF6U-Ry1tiQ1z"
        },
        {
            "id": "56",
            "vote": "Mark Jones (Party B)",
            "code": "ZZRrSiM1dSJOVQk-ApE0ItmB"
        },
        {
            "id": "59",
            "vote": "James Davies (Party G)",
            "code": "cc1BR395LTQaV9k-vNG8C53Z"
        },
        {
            "id": "60",
            "vote": "James Davies (Party G)",
            "code": "cd561hwpcBkfkTL-yBgE6Zsi"
        },
        {
            "id": "63",
            "vote": "Mark Jones (Party B)",
            "code": "eaKiFilqBqVye9U-PJt4N4Il"
        },
        {
            "id": "66",
            "vote": "Alice Smith (Party A)",
            "code": "gur8ijnG-kS9xXIvC"
        },
        {
            "id": "67",
            "vote": "Sarah Wilson (Party F)",
            "code": "hJ6fPV8X-SWbN4lZ9"
        },
        {
            "id": "68",
            "vote": "Mark Jones (Party B)",
            "code": "hXY2RtkymN6UKqV-0jPpXcOQ"
        },
        {
            "id": "71",
            "vote": "Mark Jones (Party B)",
            "code": "i3iwhBuKv6tQu6F-WVN1lt6m"
        },
        {
            "id": "72",
            "vote": "Alice Smith (Party A)",
            "code": "jOtcDLmB-pKaKU5bH"
        },
        {
            "id": "73",
            "vote": "Mark Jones (Party B)",
            "code": "jQXNZy3GQAY1PBb-pfFjG9E4"
        },
        {
            "id": "75",
            "vote": "Mark Jones (Party B)",
            "code": "kYTv7u3k0Pj11C8-FtoUxoXB"
        },
        {
            "id": "76",
            "vote": "James Davies (Party G)",
            "code": "khfDYwe4-xm0WRvIc"
        },
        {
            "id": "77",
            "vote": "Sarah Wilson (Party F)",
            "code": "lsiehFwDICXprxo-4LYI9WAr"
        },
        {
            "id": "81",
            "vote": "Alice Smith (Party A)",
            "code": "rutNrYUE6H0SdwT-ySoWaGYK"
        },
        {
            "id": "85",
            "vote": "Alice Smith (Party A)",
            "code": "tnwmbq0v-99D7Ise6"
        },
        {
            "id": "86",
            "vote": "James Davies (Party G)",
            "code": "ttZSDTd7sU2P7R3-nfNiGndI"
        },
        {
            "id": "91",
            "vote": "Sarah Wilson (Party F)",
            "code": "x5HwUelSfjXHKMF-mSJAtNHc"
        },
        {
            "id": "92",
            "vote": "Alice Smith (Party A)",
            "code": "xCzgNLMz-givd0RTd"
        },
        {
            "id": "93",
            "vote": "James Davies (Party G)",
            "code": "y77RaheQ-TSBzR5yx"
        },
        {
            "id": "94",
            "vote": "Sarah Wilson (Party F)",
            "code": "yI0tpSnI-mHKK6Iye"
        },
        {
            "id": "95",
            "vote": "Sarah Wilson (Party F)",
            "code": "ydElSJfi7J1UbMo-ERjlxpBi"
        }
  
    ]
  }